cutepandas/__init__.py
cutepandas/constants/iconnames.py
cutepandas/pandasmodels/__init__.py
cutepandas/pandasmodels/pandascategorylistmodel.py
cutepandas/pandasmodels/pandascolumnlistmodel.py
cutepandas/pandasmodels/pandasdataframemodel.py
cutepandas/pandasmodels/pandasindexfilterproxymodel.py
cutepandas/pandasmodels/polarsdataframemodel.py
cutepandas/pandaswidgets/__init__.py
cutepandas/pandaswidgets/dataframelistwidget.py
cutepandas/pandaswidgets/dataframemanagerwidget.py
cutepandas/pandaswidgets/dataframeviewer.py
cutepandas/pandaswidgets/dataframeviewer2.py
cutepandas/pandaswidgets/dataframewidget.py
cutepandas/py.typed
cutepandas/qtframe/__init__.py
cutepandas/qtframe/qtframe.py
cutepandas/utils/__init__.py
cutepandas/utils/helpers.py
cutepandas/utils/icons.py
cutepandas-0.3.2.dist-info/LICENSE
cutepandas-0.3.2.dist-info/METADATA
cutepandas-0.3.2.dist-info/WHEEL
cutepandas-0.3.2.dist-info/RECORD
