Metadata-Version: 2.1
Name: cutepandas
Version: 0.3.2
Summary: Qt Widgets and Objects for Pandas datastructures
Home-page: https://github.com/phil65/cutepandas
Author: phil65
Author-email: philipptemminghoff@googlemail.com
Requires-Python: >=3.10,<3.12
Classifier: Programming Language :: Python :: 3
Classifier: Programming Language :: Python :: 3.10
Classifier: Programming Language :: Python :: 3.11
Provides-Extra: addons
Provides-Extra: pyqt6
Provides-Extra: pyside6
Requires-Dist: PyQt6 (>=6.5,<7.0) ; extra == "pyqt6"
Requires-Dist: PyQt6-Charts (>=6.5,<7.0) ; extra == "pyqt6"
Requires-Dist: PyQt6-QScintilla (>=2.0,<3.0) ; extra == "pyqt6"
Requires-Dist: PyQt6-WebEngine (>=6.5,<7.0) ; extra == "pyqt6"
Requires-Dist: pandas
Requires-Dist: prettyqt
Requires-Dist: pyside6 (>=6.5,<7.0) ; extra == "pyside6"
Project-URL: Repository, https://github.com/phil65/cutepandas
